enterprise_utils/__init__.py
enterprise_utils/py.typed
enterprise_utils/_jsii/__init__.py
enterprise_utils/_jsii/enterprise-utils@0.0.36.jsii.tgz
enterprise_utils-0.0.36.dist-info/LICENSE
enterprise_utils-0.0.36.dist-info/METADATA
enterprise_utils-0.0.36.dist-info/WHEEL
enterprise_utils-0.0.36.dist-info/top_level.txt
enterprise_utils-0.0.36.dist-info/RECORD
